nsfw_image_detector/__init__.py
nsfw_image_detector/detector.py
nsfw_image_detector-0.1.2.dist-info/METADATA
nsfw_image_detector-0.1.2.dist-info/WHEEL
nsfw_image_detector-0.1.2.dist-info/top_level.txt
nsfw_image_detector-0.1.2.dist-info/RECORD
